tfmock/__init__.py
tfmock/db.py
tfmock/mock_server.py
tfmock/predict.py
tfmock/cloud_services/__init__.py
tfmock/cloud_services/azure/__init__.py
tfmock/cloud_services/azure/azure.py
tfmock/cloud_services/azure/services/__init__.py
tfmock/cloud_services/azure/services/msi.py
tfmock/cloud_services/azure/services/vmss.py
tfmock/proxy/__init__.py
tfmock/proxy/ca.crt
tfmock/proxy/ca.key
tfmock/proxy/cert.key
tfmock/proxy/proxy2.py
tfmock/proxy/setup_https_intercept.sh
tfmock-0.0.10.dist-info/METADATA
tfmock-0.0.10.dist-info/WHEEL
tfmock-0.0.10.dist-info/top_level.txt
tfmock-0.0.10.dist-info/RECORD
