Metadata-Version: 2.1
Name: tfmock
Version: 0.0.10
